[
  {
    "rssi": -52.99,
    "noise": -97.23,
    "transmit_rate": 228.21,
    "date": "2025-03-19T17:14:03.750217+01:00"
  },
  {
    "rssi": -52.71,
    "noise": -96.97,
    "transmit_rate": 232.57,
    "date": "2025-03-19T17:14:03.759664+01:00"
  },
  {
    "rssi": -52.99,
    "noise": -96.86,
    "transmit_rate": 226.16,
    "date": "2025-03-19T17:14:03.770597+01:00"
  },
  {
    "rssi": -52.9,
    "noise": -97.24,
    "transmit_rate": 230.9,
    "date": "2025-03-19T17:14:03.781409+01:00"
  },
  {
    "rssi": -53.24,
    "noise": -97.24,
    "transmit_rate": 231.88,
    "date": "2025-03-19T17:14:03.793363+01:00"
  },
  {
    "rssi": -53.24,
    "noise": -96.92,
    "transmit_rate": 233.1,
    "date": "2025-03-19T17:14:03.80475+01:00"
  },
  {
    "rssi": -53.25,
    "noise": -97.15,
    "transmit_rate": 224.25,
    "date": "2025-03-19T17:14:03.814892+01:00"
  },
  {
    "rssi": -51.77,
    "noise": -97.13,
    "transmit_rate": 227.82,
    "date": "2025-03-19T17:14:03.82534+01:00"
  },
  {
    "rssi": -50.9,
    "noise": -97.08,
    "transmit_rate": 229.19,
    "date": "2025-03-19T17:14:03.836673+01:00"
  },
  {
    "rssi": -51,
    "noise": -97.22,
    "transmit_rate": 229.73,
    "date": "2025-03-19T17:14:03.847268+01:00"
  },
  {
    "rssi": -50.95,
    "noise": -97.22,
    "transmit_rate": 228.31,
    "date": "2025-03-19T17:14:03.857901+01:00"
  },
  {
    "rssi": -50.95,
    "noise": -97.12,
    "transmit_rate": 229.11,
    "date": "2025-03-19T17:14:03.868442+01:00"
  },
  {
    "rssi": -51.04,
    "noise": -96.85,
    "transmit_rate": 233.93,
    "date": "2025-03-19T17:14:03.878737+01:00"
  },
  {
    "rssi": -50.97,
    "noise": -96.7,
    "transmit_rate": 232.5,
    "date": "2025-03-19T17:14:03.889628+01:00"
  },
  {
    "rssi": -50.87,
    "noise": -96.77,
    "transmit_rate": 233.58,
    "date": "2025-03-19T17:14:03.900211+01:00"
  },
  {
    "rssi": -51.04,
    "noise": -96.84,
    "transmit_rate": 232.1,
    "date": "2025-03-19T17:14:03.9102+01:00"
  },
  {
    "rssi": -51.11,
    "noise": -96.78,
    "transmit_rate": 227.32,
    "date": "2025-03-19T17:14:03.920772+01:00"
  },
  {
    "rssi": -52.25,
    "noise": -97.26,
    "transmit_rate": 226.8,
    "date": "2025-03-19T17:14:03.932292+01:00"
  },
  {
    "rssi": -52.19,
    "noise": -97.19,
    "transmit_rate": 230.2,
    "date": "2025-03-19T17:14:03.943031+01:00"
  },
  {
    "rssi": -51.88,
    "noise": -96.81,
    "transmit_rate": 225.33,
    "date": "2025-03-19T17:14:03.953828+01:00"
  },
  {
    "rssi": -51.92,
    "noise": -96.95,
    "transmit_rate": 229.65,
    "date": "2025-03-19T17:14:03.964578+01:00"
  },
  {
    "rssi": -51.85,
    "noise": -96.77,
    "transmit_rate": 226.54,
    "date": "2025-03-19T17:14:03.974927+01:00"
  },
  {
    "rssi": -52.14,
    "noise": -97.09,
    "transmit_rate": 226.87,
    "date": "2025-03-19T17:14:03.985839+01:00"
  },
  {
    "rssi": -51.98,
    "noise": -96.71,
    "transmit_rate": 225.74,
    "date": "2025-03-19T17:14:03.996235+01:00"
  },
  {
    "rssi": -52.27,
    "noise": -96.75,
    "transmit_rate": 224.43,
    "date": "2025-03-19T17:14:04.007166+01:00"
  },
  {
    "rssi": -51.73,
    "noise": -97.2,
    "transmit_rate": 231.23,
    "date": "2025-03-19T17:14:04.016984+01:00"
  },
  {
    "rssi": -51.78,
    "noise": -97.16,
    "transmit_rate": 228.39,
    "date": "2025-03-19T17:14:04.027828+01:00"
  },
  {
    "rssi": -51.73,
    "noise": -96.84,
    "transmit_rate": 227.23,
    "date": "2025-03-19T17:14:04.039759+01:00"
  },
  {
    "rssi": -51.86,
    "noise": -97.22,
    "transmit_rate": 224.28,
    "date": "2025-03-19T17:14:04.049712+01:00"
  },
  {
    "rssi": -51.87,
    "noise": -96.97,
    "transmit_rate": 225.89,
    "date": "2025-03-19T17:14:04.060831+01:00"
  },
  {
    "rssi": -51.85,
    "noise": -97.18,
    "transmit_rate": 231.08,
    "date": "2025-03-19T17:14:04.071644+01:00"
  },
  {
    "rssi": -51.84,
    "noise": -96.88,
    "transmit_rate": 230.96,
    "date": "2025-03-19T17:14:04.082029+01:00"
  },
  {
    "rssi": -52.15,
    "noise": -97.04,
    "transmit_rate": 226.4,
    "date": "2025-03-19T17:14:04.093552+01:00"
  },
  {
    "rssi": -52.09,
    "noise": -97.17,
    "transmit_rate": 231.28,
    "date": "2025-03-19T17:14:04.103724+01:00"
  },
  {
    "rssi": -51.89,
    "noise": -97.07,
    "transmit_rate": 227.95,
    "date": "2025-03-19T17:14:04.114147+01:00"
  },
  {
    "rssi": -52.02,
    "noise": -97.09,
    "transmit_rate": 229.07,
    "date": "2025-03-19T17:14:04.122011+01:00"
  },
  {
    "rssi": -52.02,
    "noise": -97.28,
    "transmit_rate": 232.8,
    "date": "2025-03-19T17:14:04.133908+01:00"
  },
  {
    "rssi": -52.26,
    "noise": -96.78,
    "transmit_rate": 228.19,
    "date": "2025-03-19T17:14:04.144398+01:00"
  },
  {
    "rssi": -51.98,
    "noise": -96.75,
    "transmit_rate": 232.31,
    "date": "2025-03-19T17:14:04.155354+01:00"
  },
  {
    "rssi": -51.76,
    "noise": -96.96,
    "transmit_rate": 225.97,
    "date": "2025-03-19T17:14:04.167278+01:00"
  },
  {
    "rssi": -51.82,
    "noise": -97.19,
    "transmit_rate": 225.59,
    "date": "2025-03-19T17:14:04.17741+01:00"
  },
  {
    "rssi": -52.18,
    "noise": -97.04,
    "transmit_rate": 229.49,
    "date": "2025-03-19T17:14:04.186672+01:00"
  },
  {
    "rssi": -51.96,
    "noise": -97.23,
    "transmit_rate": 231.43,
    "date": "2025-03-19T17:14:04.197157+01:00"
  },
  {
    "rssi": -52.18,
    "noise": -96.91,
    "transmit_rate": 232.76,
    "date": "2025-03-19T17:14:04.207791+01:00"
  },
  {
    "rssi": -51.82,
    "noise": -97.01,
    "transmit_rate": 230.35,
    "date": "2025-03-19T17:14:04.217819+01:00"
  },
  {
    "rssi": -52.21,
    "noise": -97.1,
    "transmit_rate": 231.25,
    "date": "2025-03-19T17:14:04.227835+01:00"
  },
  {
    "rssi": -50.77,
    "noise": -97.01,
    "transmit_rate": 233.91,
    "date": "2025-03-19T17:14:04.239972+01:00"
  },
  {
    "rssi": -51.13,
    "noise": -96.8,
    "transmit_rate": 230.47,
    "date": "2025-03-19T17:14:04.250439+01:00"
  },
  {
    "rssi": -51.1,
    "noise": -96.97,
    "transmit_rate": 229.46,
    "date": "2025-03-19T17:14:04.260914+01:00"
  },
  {
    "rssi": -50.91,
    "noise": -97.2,
    "transmit_rate": 228.06,
    "date": "2025-03-19T17:14:04.273204+01:00"
  },
  {
    "rssi": -50.99,
    "noise": -97,
    "transmit_rate": 233.24,
    "date": "2025-03-19T17:14:04.283599+01:00"
  },
  {
    "rssi": -51.27,
    "noise": -96.86,
    "transmit_rate": 224.5,
    "date": "2025-03-19T17:14:04.293879+01:00"
  },
  {
    "rssi": -50.92,
    "noise": -96.76,
    "transmit_rate": 224.99,
    "date": "2025-03-19T17:14:04.302926+01:00"
  },
  {
    "rssi": -50.82,
    "noise": -97.11,
    "transmit_rate": 225.99,
    "date": "2025-03-19T17:14:04.313304+01:00"
  },
  {
    "rssi": -50.9,
    "noise": -97.07,
    "transmit_rate": 228.86,
    "date": "2025-03-19T17:14:04.322979+01:00"
  },
  {
    "rssi": -50.9,
    "noise": -97.22,
    "transmit_rate": 229.45,
    "date": "2025-03-19T17:14:04.336398+01:00"
  },
  {
    "rssi": -50.82,
    "noise": -97.3,
    "transmit_rate": 229.57,
    "date": "2025-03-19T17:14:04.346744+01:00"
  },
  {
    "rssi": -51.26,
    "noise": -96.9,
    "transmit_rate": 228.76,
    "date": "2025-03-19T17:14:04.357004+01:00"
  },
  {
    "rssi": -50.84,
    "noise": -97.17,
    "transmit_rate": 230.97,
    "date": "2025-03-19T17:14:04.365838+01:00"
  },
  {
    "rssi": -51.3,
    "noise": -96.99,
    "transmit_rate": 232.44,
    "date": "2025-03-19T17:14:04.376313+01:00"
  },
  {
    "rssi": -50.86,
    "noise": -96.88,
    "transmit_rate": 224.91,
    "date": "2025-03-19T17:14:04.387018+01:00"
  },
  {
    "rssi": -50.85,
    "noise": -96.84,
    "transmit_rate": 228.15,
    "date": "2025-03-19T17:14:04.399183+01:00"
  },
  {
    "rssi": -50.9,
    "noise": -96.7,
    "transmit_rate": 224.07,
    "date": "2025-03-19T17:14:04.409568+01:00"
  },
  {
    "rssi": -51.09,
    "noise": -97.1,
    "transmit_rate": 232.09,
    "date": "2025-03-19T17:14:04.418538+01:00"
  },
  {
    "rssi": -50.85,
    "noise": -97.08,
    "transmit_rate": 231.92,
    "date": "2025-03-19T17:14:04.427985+01:00"
  },
  {
    "rssi": -51,
    "noise": -96.76,
    "transmit_rate": 228.48,
    "date": "2025-03-19T17:14:04.439631+01:00"
  },
  {
    "rssi": -51.07,
    "noise": -97.24,
    "transmit_rate": 231.85,
    "date": "2025-03-19T17:14:04.449979+01:00"
  },
  {
    "rssi": -51.1,
    "noise": -97.09,
    "transmit_rate": 231.35,
    "date": "2025-03-19T17:14:04.461901+01:00"
  },
  {
    "rssi": -51.18,
    "noise": -97.13,
    "transmit_rate": 228.24,
    "date": "2025-03-19T17:14:04.472373+01:00"
  },
  {
    "rssi": -51.02,
    "noise": -96.72,
    "transmit_rate": 230.15,
    "date": "2025-03-19T17:14:04.481354+01:00"
  },
  {
    "rssi": -50.85,
    "noise": -97.19,
    "transmit_rate": 224.92,
    "date": "2025-03-19T17:14:04.491902+01:00"
  },
  {
    "rssi": -51.19,
    "noise": -97.05,
    "transmit_rate": 224.23,
    "date": "2025-03-19T17:14:04.502223+01:00"
  },
  {
    "rssi": -50.87,
    "noise": -96.86,
    "transmit_rate": 225.67,
    "date": "2025-03-19T17:14:04.514241+01:00"
  },
  {
    "rssi": -51.21,
    "noise": -96.85,
    "transmit_rate": 229.55,
    "date": "2025-03-19T17:14:04.5242+01:00"
  },
  {
    "rssi": -50.93,
    "noise": -97.21,
    "transmit_rate": 232.43,
    "date": "2025-03-19T17:14:04.532613+01:00"
  },
  {
    "rssi": -50.74,
    "noise": -97.24,
    "transmit_rate": 231.41,
    "date": "2025-03-19T17:14:04.544402+01:00"
  },
  {
    "rssi": -51.11,
    "noise": -96.85,
    "transmit_rate": 225.7,
    "date": "2025-03-19T17:14:04.555275+01:00"
  },
  {
    "rssi": -50.88,
    "noise": -97.16,
    "transmit_rate": 232.36,
    "date": "2025-03-19T17:14:04.565851+01:00"
  },
  {
    "rssi": -51.29,
    "noise": -97.11,
    "transmit_rate": 225.69,
    "date": "2025-03-19T17:14:04.577419+01:00"
  },
  {
    "rssi": -51.22,
    "noise": -97.07,
    "transmit_rate": 225.95,
    "date": "2025-03-19T17:14:04.588018+01:00"
  },
  {
    "rssi": -50.88,
    "noise": -96.71,
    "transmit_rate": 225.05,
    "date": "2025-03-19T17:14:04.597565+01:00"
  },
  {
    "rssi": -51.01,
    "noise": -96.9,
    "transmit_rate": 224.96,
    "date": "2025-03-19T17:14:04.607544+01:00"
  },
  {
    "rssi": -50.92,
    "noise": -97.23,
    "transmit_rate": 225.01,
    "date": "2025-03-19T17:14:04.618183+01:00"
  },
  {
    "rssi": -50.84,
    "noise": -96.73,
    "transmit_rate": 225.58,
    "date": "2025-03-19T17:14:04.627617+01:00"
  },
  {
    "rssi": -50.82,
    "noise": -97.24,
    "transmit_rate": 228.52,
    "date": "2025-03-19T17:14:04.638532+01:00"
  },
  {
    "rssi": -51.97,
    "noise": -96.74,
    "transmit_rate": 228.68,
    "date": "2025-03-19T17:14:04.649392+01:00"
  },
  {
    "rssi": -52.2,
    "noise": -97.04,
    "transmit_rate": 227.72,
    "date": "2025-03-19T17:14:04.66099+01:00"
  },
  {
    "rssi": -51.76,
    "noise": -97.21,
    "transmit_rate": 228.92,
    "date": "2025-03-19T17:14:04.671869+01:00"
  },
  {
    "rssi": -52.23,
    "noise": -97.24,
    "transmit_rate": 226.97,
    "date": "2025-03-19T17:14:04.682529+01:00"
  },
  {
    "rssi": -52.12,
    "noise": -97.06,
    "transmit_rate": 233.53,
    "date": "2025-03-19T17:14:04.692976+01:00"
  },
  {
    "rssi": -51.98,
    "noise": -96.99,
    "transmit_rate": 230.26,
    "date": "2025-03-19T17:14:04.705058+01:00"
  },
  {
    "rssi": -51.97,
    "noise": -96.86,
    "transmit_rate": 226.71,
    "date": "2025-03-19T17:14:04.715459+01:00"
  },
  {
    "rssi": -52.03,
    "noise": -97.29,
    "transmit_rate": 229.18,
    "date": "2025-03-19T17:14:04.724445+01:00"
  },
  {
    "rssi": -51.94,
    "noise": -97.23,
    "transmit_rate": 230.01,
    "date": "2025-03-19T17:14:04.734031+01:00"
  },
  {
    "rssi": -51.97,
    "noise": -97.22,
    "transmit_rate": 232.8,
    "date": "2025-03-19T17:14:04.744716+01:00"
  },
  {
    "rssi": -51.9,
    "noise": -97.03,
    "transmit_rate": 230.13,
    "date": "2025-03-19T17:14:04.756323+01:00"
  },
  {
    "rssi": -52.12,
    "noise": -97.13,
    "transmit_rate": 231.81,
    "date": "2025-03-19T17:14:04.767286+01:00"
  },
  {
    "rssi": -51.95,
    "noise": -97.05,
    "transmit_rate": 225.54,
    "date": "2025-03-19T17:14:04.776989+01:00"
  },
  {
    "rssi": -52.04,
    "noise": -96.74,
    "transmit_rate": 225.98,
    "date": "2025-03-19T17:14:04.788329+01:00"
  },
  {
    "rssi": -52.12,
    "noise": -96.71,
    "transmit_rate": 232.33,
    "date": "2025-03-19T17:14:04.798945+01:00"
  }
]