[
  {
    "rssi": -62.95,
    "noise": -92.98,
    "transmit_rate": 457.2,
    "date": "2025-03-20T12:06:23.867938+01:00"
  },
  {
    "rssi": -62.83,
    "noise": -92.71,
    "transmit_rate": 455.04,
    "date": "2025-03-20T12:06:23.875919+01:00"
  },
  {
    "rssi": -63.12,
    "noise": -93.07,
    "transmit_rate": 460.09,
    "date": "2025-03-20T12:06:23.886898+01:00"
  },
  {
    "rssi": -63,
    "noise": -93.08,
    "transmit_rate": 453.83,
    "date": "2025-03-20T12:06:23.897493+01:00"
  },
  {
    "rssi": -62.7,
    "noise": -92.9,
    "transmit_rate": 459.22,
    "date": "2025-03-20T12:06:23.908464+01:00"
  },
  {
    "rssi": -62.73,
    "noise": -93.28,
    "transmit_rate": 458.33,
    "date": "2025-03-20T12:06:23.919758+01:00"
  },
  {
    "rssi": -62.84,
    "noise": -92.89,
    "transmit_rate": 457.82,
    "date": "2025-03-20T12:06:23.930056+01:00"
  },
  {
    "rssi": -63.13,
    "noise": -92.92,
    "transmit_rate": 457.6,
    "date": "2025-03-20T12:06:23.940674+01:00"
  },
  {
    "rssi": -62.72,
    "noise": -93.11,
    "transmit_rate": 457.69,
    "date": "2025-03-20T12:06:23.950808+01:00"
  },
  {
    "rssi": -62.71,
    "noise": -92.8,
    "transmit_rate": 456.48,
    "date": "2025-03-20T12:06:23.961117+01:00"
  },
  {
    "rssi": -62.95,
    "noise": -92.72,
    "transmit_rate": 462.75,
    "date": "2025-03-20T12:06:23.973045+01:00"
  },
  {
    "rssi": -63.06,
    "noise": -93.17,
    "transmit_rate": 457.02,
    "date": "2025-03-20T12:06:23.983589+01:00"
  },
  {
    "rssi": -63.01,
    "noise": -93.07,
    "transmit_rate": 455.71,
    "date": "2025-03-20T12:06:23.994323+01:00"
  },
  {
    "rssi": -62.71,
    "noise": -92.7,
    "transmit_rate": 457.41,
    "date": "2025-03-20T12:06:24.005135+01:00"
  },
  {
    "rssi": -63.03,
    "noise": -92.71,
    "transmit_rate": 461.87,
    "date": "2025-03-20T12:06:24.015602+01:00"
  },
  {
    "rssi": -63.07,
    "noise": -92.92,
    "transmit_rate": 458.27,
    "date": "2025-03-20T12:06:24.026063+01:00"
  },
  {
    "rssi": -63.12,
    "noise": -92.76,
    "transmit_rate": 460.79,
    "date": "2025-03-20T12:06:24.036893+01:00"
  },
  {
    "rssi": -64.14,
    "noise": -92.94,
    "transmit_rate": 460.39,
    "date": "2025-03-20T12:06:24.047271+01:00"
  },
  {
    "rssi": -64.3,
    "noise": -93.18,
    "transmit_rate": 453.8,
    "date": "2025-03-20T12:06:24.058633+01:00"
  },
  {
    "rssi": -64.26,
    "noise": -92.88,
    "transmit_rate": 459.91,
    "date": "2025-03-20T12:06:24.068836+01:00"
  },
  {
    "rssi": -64.04,
    "noise": -92.82,
    "transmit_rate": 455.11,
    "date": "2025-03-20T12:06:24.079731+01:00"
  },
  {
    "rssi": -63.97,
    "noise": -92.97,
    "transmit_rate": 457.08,
    "date": "2025-03-20T12:06:24.091891+01:00"
  },
  {
    "rssi": -63.83,
    "noise": -92.83,
    "transmit_rate": 457.16,
    "date": "2025-03-20T12:06:24.100125+01:00"
  },
  {
    "rssi": -63.99,
    "noise": -93.28,
    "transmit_rate": 453.78,
    "date": "2025-03-20T12:06:24.111664+01:00"
  },
  {
    "rssi": -64.18,
    "noise": -92.93,
    "transmit_rate": 459.89,
    "date": "2025-03-20T12:06:24.12139+01:00"
  },
  {
    "rssi": -64.03,
    "noise": -92.79,
    "transmit_rate": 458.44,
    "date": "2025-03-20T12:06:24.133854+01:00"
  },
  {
    "rssi": -63.86,
    "noise": -92.71,
    "transmit_rate": 461.37,
    "date": "2025-03-20T12:06:24.1432+01:00"
  },
  {
    "rssi": -64.03,
    "noise": -92.73,
    "transmit_rate": 456.13,
    "date": "2025-03-20T12:06:24.154378+01:00"
  },
  {
    "rssi": -63.87,
    "noise": -93.23,
    "transmit_rate": 456.64,
    "date": "2025-03-20T12:06:24.165674+01:00"
  },
  {
    "rssi": -64.23,
    "noise": -92.88,
    "transmit_rate": 454.27,
    "date": "2025-03-20T12:06:24.176365+01:00"
  },
  {
    "rssi": -64.22,
    "noise": -92.7,
    "transmit_rate": 455.05,
    "date": "2025-03-20T12:06:24.186726+01:00"
  },
  {
    "rssi": -63.73,
    "noise": -92.75,
    "transmit_rate": 455.42,
    "date": "2025-03-20T12:06:24.196096+01:00"
  },
  {
    "rssi": -64.3,
    "noise": -93.27,
    "transmit_rate": 454.99,
    "date": "2025-03-20T12:06:24.207771+01:00"
  },
  {
    "rssi": -63.79,
    "noise": -93.17,
    "transmit_rate": 460.14,
    "date": "2025-03-20T12:06:24.218327+01:00"
  },
  {
    "rssi": -64.08,
    "noise": -92.81,
    "transmit_rate": 457.19,
    "date": "2025-03-20T12:06:24.22958+01:00"
  },
  {
    "rssi": -64.18,
    "noise": -92.92,
    "transmit_rate": 453.21,
    "date": "2025-03-20T12:06:24.239423+01:00"
  },
  {
    "rssi": -64.18,
    "noise": -92.92,
    "transmit_rate": 459.96,
    "date": "2025-03-20T12:06:24.251119+01:00"
  },
  {
    "rssi": -64.06,
    "noise": -92.79,
    "transmit_rate": 462.39,
    "date": "2025-03-20T12:06:24.260806+01:00"
  },
  {
    "rssi": -64.28,
    "noise": -92.77,
    "transmit_rate": 460.83,
    "date": "2025-03-20T12:06:24.272884+01:00"
  },
  {
    "rssi": -64.05,
    "noise": -92.86,
    "transmit_rate": 458.77,
    "date": "2025-03-20T12:06:24.2828+01:00"
  },
  {
    "rssi": -64.2,
    "noise": -93.02,
    "transmit_rate": 460.5,
    "date": "2025-03-20T12:06:24.292947+01:00"
  },
  {
    "rssi": -64.14,
    "noise": -93.18,
    "transmit_rate": 455.31,
    "date": "2025-03-20T12:06:24.304884+01:00"
  },
  {
    "rssi": -63.72,
    "noise": -93.17,
    "transmit_rate": 461.67,
    "date": "2025-03-20T12:06:24.315949+01:00"
  },
  {
    "rssi": -64.3,
    "noise": -92.94,
    "transmit_rate": 454.43,
    "date": "2025-03-20T12:06:24.325482+01:00"
  },
  {
    "rssi": -64.08,
    "noise": -92.77,
    "transmit_rate": 460.74,
    "date": "2025-03-20T12:06:24.33706+01:00"
  },
  {
    "rssi": -63.77,
    "noise": -93.09,
    "transmit_rate": 461.43,
    "date": "2025-03-20T12:06:24.346523+01:00"
  },
  {
    "rssi": -63.97,
    "noise": -92.8,
    "transmit_rate": 454.41,
    "date": "2025-03-20T12:06:24.358996+01:00"
  },
  {
    "rssi": -64,
    "noise": -93.29,
    "transmit_rate": 461.8,
    "date": "2025-03-20T12:06:24.370522+01:00"
  },
  {
    "rssi": -64.24,
    "noise": -93,
    "transmit_rate": 458.16,
    "date": "2025-03-20T12:06:24.379174+01:00"
  },
  {
    "rssi": -63.76,
    "noise": -93.27,
    "transmit_rate": 462.85,
    "date": "2025-03-20T12:06:24.390026+01:00"
  },
  {
    "rssi": -63.97,
    "noise": -92.98,
    "transmit_rate": 459.66,
    "date": "2025-03-20T12:06:24.401227+01:00"
  },
  {
    "rssi": -63.97,
    "noise": -93.19,
    "transmit_rate": 454.18,
    "date": "2025-03-20T12:06:24.411122+01:00"
  },
  {
    "rssi": -64.17,
    "noise": -93.02,
    "transmit_rate": 456.22,
    "date": "2025-03-20T12:06:24.42278+01:00"
  },
  {
    "rssi": -63.81,
    "noise": -93.18,
    "transmit_rate": 458.71,
    "date": "2025-03-20T12:06:24.433017+01:00"
  },
  {
    "rssi": -64.11,
    "noise": -93.05,
    "transmit_rate": 462.96,
    "date": "2025-03-20T12:06:24.444193+01:00"
  },
  {
    "rssi": -63.93,
    "noise": -92.97,
    "transmit_rate": 453.84,
    "date": "2025-03-20T12:06:24.454008+01:00"
  },
  {
    "rssi": -63.78,
    "noise": -92.76,
    "transmit_rate": 453.08,
    "date": "2025-03-20T12:06:24.464728+01:00"
  },
  {
    "rssi": -63.88,
    "noise": -92.91,
    "transmit_rate": 457.11,
    "date": "2025-03-20T12:06:24.474854+01:00"
  },
  {
    "rssi": -64.04,
    "noise": -93.15,
    "transmit_rate": 458.26,
    "date": "2025-03-20T12:06:24.487353+01:00"
  },
  {
    "rssi": -63.78,
    "noise": -92.73,
    "transmit_rate": 454.44,
    "date": "2025-03-20T12:06:24.496295+01:00"
  },
  {
    "rssi": -64.18,
    "noise": -92.99,
    "transmit_rate": 458.46,
    "date": "2025-03-20T12:06:24.50726+01:00"
  },
  {
    "rssi": -63.93,
    "noise": -92.84,
    "transmit_rate": 459.72,
    "date": "2025-03-20T12:06:24.518522+01:00"
  },
  {
    "rssi": -63.98,
    "noise": -92.83,
    "transmit_rate": 455.56,
    "date": "2025-03-20T12:06:24.528551+01:00"
  },
  {
    "rssi": -64.08,
    "noise": -92.75,
    "transmit_rate": 460.78,
    "date": "2025-03-20T12:06:24.539434+01:00"
  },
  {
    "rssi": -63.95,
    "noise": -92.82,
    "transmit_rate": 460.52,
    "date": "2025-03-20T12:06:24.551234+01:00"
  },
  {
    "rssi": -63.85,
    "noise": -93.24,
    "transmit_rate": 462.14,
    "date": "2025-03-20T12:06:24.561508+01:00"
  },
  {
    "rssi": -64.22,
    "noise": -92.79,
    "transmit_rate": 461.08,
    "date": "2025-03-20T12:06:24.571574+01:00"
  },
  {
    "rssi": -63.75,
    "noise": -92.77,
    "transmit_rate": 456.94,
    "date": "2025-03-20T12:06:24.582003+01:00"
  },
  {
    "rssi": -64.07,
    "noise": -93.01,
    "transmit_rate": 457.47,
    "date": "2025-03-20T12:06:24.591991+01:00"
  },
  {
    "rssi": -64.09,
    "noise": -92.86,
    "transmit_rate": 458.58,
    "date": "2025-03-20T12:06:24.603749+01:00"
  },
  {
    "rssi": -64.19,
    "noise": -93.2,
    "transmit_rate": 456.52,
    "date": "2025-03-20T12:06:24.613162+01:00"
  },
  {
    "rssi": -63.76,
    "noise": -92.79,
    "transmit_rate": 460.97,
    "date": "2025-03-20T12:06:24.625145+01:00"
  },
  {
    "rssi": -63.87,
    "noise": -93.03,
    "transmit_rate": 460.92,
    "date": "2025-03-20T12:06:24.635262+01:00"
  },
  {
    "rssi": -63.93,
    "noise": -93,
    "transmit_rate": 456.6,
    "date": "2025-03-20T12:06:24.646074+01:00"
  },
  {
    "rssi": -65.11,
    "noise": -92.9,
    "transmit_rate": 461.49,
    "date": "2025-03-20T12:06:24.658661+01:00"
  },
  {
    "rssi": -64.97,
    "noise": -93.06,
    "transmit_rate": 461.67,
    "date": "2025-03-20T12:06:24.666383+01:00"
  },
  {
    "rssi": -64.82,
    "noise": -93.15,
    "transmit_rate": 454.73,
    "date": "2025-03-20T12:06:24.677886+01:00"
  },
  {
    "rssi": -64.76,
    "noise": -92.94,
    "transmit_rate": 456.7,
    "date": "2025-03-20T12:06:24.691843+01:00"
  },
  {
    "rssi": -65.16,
    "noise": -92.78,
    "transmit_rate": 459.24,
    "date": "2025-03-20T12:06:24.701766+01:00"
  },
  {
    "rssi": -65.2,
    "noise": -92.71,
    "transmit_rate": 461.42,
    "date": "2025-03-20T12:06:24.712637+01:00"
  },
  {
    "rssi": -65.11,
    "noise": -92.9,
    "transmit_rate": 457.64,
    "date": "2025-03-20T12:06:24.722543+01:00"
  },
  {
    "rssi": -65.26,
    "noise": -93,
    "transmit_rate": 462.04,
    "date": "2025-03-20T12:06:24.733458+01:00"
  },
  {
    "rssi": -65.16,
    "noise": -92.72,
    "transmit_rate": 453.12,
    "date": "2025-03-20T12:06:24.744277+01:00"
  },
  {
    "rssi": -64.78,
    "noise": -93.14,
    "transmit_rate": 456.85,
    "date": "2025-03-20T12:06:24.756679+01:00"
  },
  {
    "rssi": -65.24,
    "noise": -92.88,
    "transmit_rate": 460.72,
    "date": "2025-03-20T12:06:24.764857+01:00"
  },
  {
    "rssi": -65.18,
    "noise": -93.1,
    "transmit_rate": 456.4,
    "date": "2025-03-20T12:06:24.776244+01:00"
  },
  {
    "rssi": -65.04,
    "noise": -92.72,
    "transmit_rate": 462.54,
    "date": "2025-03-20T12:06:24.7864+01:00"
  },
  {
    "rssi": -65.2,
    "noise": -93.22,
    "transmit_rate": 455.83,
    "date": "2025-03-20T12:06:24.797584+01:00"
  },
  {
    "rssi": -65.23,
    "noise": -92.75,
    "transmit_rate": 458.86,
    "date": "2025-03-20T12:06:24.807885+01:00"
  },
  {
    "rssi": -64.71,
    "noise": -93.03,
    "transmit_rate": 457.82,
    "date": "2025-03-20T12:06:24.818021+01:00"
  },
  {
    "rssi": -65.18,
    "noise": -93.13,
    "transmit_rate": 460.5,
    "date": "2025-03-20T12:06:24.828875+01:00"
  },
  {
    "rssi": -65,
    "noise": -92.96,
    "transmit_rate": 455.36,
    "date": "2025-03-20T12:06:24.839286+01:00"
  },
  {
    "rssi": -64.91,
    "noise": -93.08,
    "transmit_rate": 454.12,
    "date": "2025-03-20T12:06:24.84978+01:00"
  },
  {
    "rssi": -64.12,
    "noise": -93.16,
    "transmit_rate": 454.71,
    "date": "2025-03-20T12:06:24.860159+01:00"
  },
  {
    "rssi": -63.98,
    "noise": -93.18,
    "transmit_rate": 459.59,
    "date": "2025-03-20T12:06:24.870926+01:00"
  },
  {
    "rssi": -64.23,
    "noise": -93.26,
    "transmit_rate": 453.41,
    "date": "2025-03-20T12:06:24.881859+01:00"
  },
  {
    "rssi": -63.98,
    "noise": -93.26,
    "transmit_rate": 455.73,
    "date": "2025-03-20T12:06:24.89449+01:00"
  },
  {
    "rssi": -64.29,
    "noise": -92.77,
    "transmit_rate": 455.26,
    "date": "2025-03-20T12:06:24.90216+01:00"
  },
  {
    "rssi": -64.2,
    "noise": -92.8,
    "transmit_rate": 458.75,
    "date": "2025-03-20T12:06:24.913229+01:00"
  },
  {
    "rssi": -63.71,
    "noise": -93.24,
    "transmit_rate": 458.44,
    "date": "2025-03-20T12:06:24.923349+01:00"
  }
]