[
  {
    "rssi": -61.25,
    "noise": -93.29,
    "transmit_rate": 0,
    "date": "2025-03-19T17:00:12.063459+01:00"
  },
  {
    "rssi": -61.28,
    "noise": -92.96,
    "transmit_rate": 0,
    "date": "2025-03-19T17:00:12.07422+01:00"
  },
  {
    "rssi": -61.12,
    "noise": -92.83,
    "transmit_rate": 0,
    "date": "2025-03-19T17:00:12.08404+01:00"
  },
  {
    "rssi": -61.26,
    "noise": -93.1,
    "transmit_rate": 0,
    "date": "2025-03-19T17:00:12.095409+01:00"
  },
  {
    "rssi": -61.16,
    "noise": -93.21,
    "transmit_rate": 0,
    "date": "2025-03-19T17:00:12.106725+01:00"
  },
  {
    "rssi": -60.79,
    "noise": -93.05,
    "transmit_rate": 0,
    "date": "2025-03-19T17:00:12.116668+01:00"
  },
  {
    "rssi": -60.91,
    "noise": -93.01,
    "transmit_rate": 0,
    "date": "2025-03-19T17:00:12.127517+01:00"
  },
  {
    "rssi": -60.73,
    "noise": -92.81,
    "transmit_rate": 0,
    "date": "2025-03-19T17:00:12.137079+01:00"
  },
  {
    "rssi": -60.89,
    "noise": -92.97,
    "transmit_rate": 0,
    "date": "2025-03-19T17:00:12.168031+01:00"
  },
  {
    "rssi": -60.73,
    "noise": -92.73,
    "transmit_rate": 0,
    "date": "2025-03-19T17:00:12.173917+01:00"
  },
  {
    "rssi": -60.99,
    "noise": -92.82,
    "transmit_rate": 0,
    "date": "2025-03-19T17:00:12.184424+01:00"
  },
  {
    "rssi": -61.1,
    "noise": -92.83,
    "transmit_rate": 0,
    "date": "2025-03-19T17:00:12.195209+01:00"
  },
  {
    "rssi": -61.28,
    "noise": -92.78,
    "transmit_rate": 0,
    "date": "2025-03-19T17:00:12.205094+01:00"
  },
  {
    "rssi": -61.08,
    "noise": -92.97,
    "transmit_rate": 0,
    "date": "2025-03-19T17:00:12.217482+01:00"
  },
  {
    "rssi": -61.05,
    "noise": -93.03,
    "transmit_rate": 0,
    "date": "2025-03-19T17:00:12.226851+01:00"
  },
  {
    "rssi": -61.29,
    "noise": -93.2,
    "transmit_rate": 0,
    "date": "2025-03-19T17:00:12.235509+01:00"
  },
  {
    "rssi": -61.26,
    "noise": -93.13,
    "transmit_rate": 0,
    "date": "2025-03-19T17:00:12.246778+01:00"
  },
  {
    "rssi": -61.08,
    "noise": -93.06,
    "transmit_rate": 0,
    "date": "2025-03-19T17:00:12.256103+01:00"
  },
  {
    "rssi": -61.06,
    "noise": -93.15,
    "transmit_rate": 0,
    "date": "2025-03-19T17:00:12.269334+01:00"
  },
  {
    "rssi": -61.17,
    "noise": -92.71,
    "transmit_rate": 0,
    "date": "2025-03-19T17:00:12.276839+01:00"
  },
  {
    "rssi": -61.03,
    "noise": -93.03,
    "transmit_rate": 0,
    "date": "2025-03-19T17:00:12.288393+01:00"
  },
  {
    "rssi": -60.84,
    "noise": -92.72,
    "transmit_rate": 0,
    "date": "2025-03-19T17:00:12.29864+01:00"
  },
  {
    "rssi": -61,
    "noise": -92.84,
    "transmit_rate": 0,
    "date": "2025-03-19T17:00:12.309066+01:00"
  },
  {
    "rssi": -61.08,
    "noise": -93.1,
    "transmit_rate": 0,
    "date": "2025-03-19T17:00:12.320322+01:00"
  },
  {
    "rssi": -61.11,
    "noise": -92.92,
    "transmit_rate": 0,
    "date": "2025-03-19T17:00:12.329044+01:00"
  },
  {
    "rssi": -61.17,
    "noise": -93.09,
    "transmit_rate": 0,
    "date": "2025-03-19T17:00:12.341041+01:00"
  },
  {
    "rssi": -61.11,
    "noise": -93,
    "transmit_rate": 0,
    "date": "2025-03-19T17:00:12.350902+01:00"
  },
  {
    "rssi": -61.19,
    "noise": -92.73,
    "transmit_rate": 0,
    "date": "2025-03-19T17:00:12.36128+01:00"
  },
  {
    "rssi": -61.04,
    "noise": -92.95,
    "transmit_rate": 0,
    "date": "2025-03-19T17:00:12.374436+01:00"
  },
  {
    "rssi": -60.79,
    "noise": -93.06,
    "transmit_rate": 0,
    "date": "2025-03-19T17:00:12.381651+01:00"
  },
  {
    "rssi": -61.11,
    "noise": -93.27,
    "transmit_rate": 0,
    "date": "2025-03-19T17:00:12.392149+01:00"
  },
  {
    "rssi": -61.03,
    "noise": -93.17,
    "transmit_rate": 0,
    "date": "2025-03-19T17:00:12.404279+01:00"
  },
  {
    "rssi": -60.99,
    "noise": -93.27,
    "transmit_rate": 0,
    "date": "2025-03-19T17:00:12.413138+01:00"
  },
  {
    "rssi": -60.77,
    "noise": -93.12,
    "transmit_rate": 0,
    "date": "2025-03-19T17:00:12.424918+01:00"
  },
  {
    "rssi": -60.8,
    "noise": -92.88,
    "transmit_rate": 0,
    "date": "2025-03-19T17:00:12.435365+01:00"
  },
  {
    "rssi": -61.2,
    "noise": -93.08,
    "transmit_rate": 0,
    "date": "2025-03-19T17:00:12.445182+01:00"
  },
  {
    "rssi": -60.93,
    "noise": -93.23,
    "transmit_rate": 0,
    "date": "2025-03-19T17:00:12.461166+01:00"
  },
  {
    "rssi": -61.09,
    "noise": -93.24,
    "transmit_rate": 0,
    "date": "2025-03-19T17:00:12.467296+01:00"
  },
  {
    "rssi": -61.17,
    "noise": -92.93,
    "transmit_rate": 0,
    "date": "2025-03-19T17:00:12.478955+01:00"
  },
  {
    "rssi": -61.1,
    "noise": -92.83,
    "transmit_rate": 0,
    "date": "2025-03-19T17:00:12.490033+01:00"
  },
  {
    "rssi": -61.27,
    "noise": -93.12,
    "transmit_rate": 0,
    "date": "2025-03-19T17:00:12.500619+01:00"
  },
  {
    "rssi": -60.76,
    "noise": -92.77,
    "transmit_rate": 0,
    "date": "2025-03-19T17:00:12.510517+01:00"
  },
  {
    "rssi": -60.87,
    "noise": -93.02,
    "transmit_rate": 0,
    "date": "2025-03-19T17:00:12.520756+01:00"
  },
  {
    "rssi": -61.25,
    "noise": -92.7,
    "transmit_rate": 0,
    "date": "2025-03-19T17:00:12.532213+01:00"
  },
  {
    "rssi": -61.12,
    "noise": -92.86,
    "transmit_rate": 0,
    "date": "2025-03-19T17:00:12.5416+01:00"
  },
  {
    "rssi": -60.87,
    "noise": -92.83,
    "transmit_rate": 0,
    "date": "2025-03-19T17:00:12.553326+01:00"
  },
  {
    "rssi": -61.07,
    "noise": -93.03,
    "transmit_rate": 0,
    "date": "2025-03-19T17:00:12.562684+01:00"
  },
  {
    "rssi": -60.7,
    "noise": -92.88,
    "transmit_rate": 0,
    "date": "2025-03-19T17:00:12.573686+01:00"
  },
  {
    "rssi": -61.1,
    "noise": -93.23,
    "transmit_rate": 0,
    "date": "2025-03-19T17:00:12.586506+01:00"
  },
  {
    "rssi": -60.86,
    "noise": -93.21,
    "transmit_rate": 0,
    "date": "2025-03-19T17:00:12.594653+01:00"
  },
  {
    "rssi": -61.19,
    "noise": -93.04,
    "transmit_rate": 0,
    "date": "2025-03-19T17:00:12.606717+01:00"
  },
  {
    "rssi": -60.87,
    "noise": -92.85,
    "transmit_rate": 0,
    "date": "2025-03-19T17:00:12.616203+01:00"
  },
  {
    "rssi": -61.23,
    "noise": -93.1,
    "transmit_rate": 0,
    "date": "2025-03-19T17:00:12.626396+01:00"
  },
  {
    "rssi": -61.26,
    "noise": -93.13,
    "transmit_rate": 0,
    "date": "2025-03-19T17:00:12.637899+01:00"
  },
  {
    "rssi": -61.18,
    "noise": -92.83,
    "transmit_rate": 0,
    "date": "2025-03-19T17:00:12.649026+01:00"
  },
  {
    "rssi": -60.85,
    "noise": -92.71,
    "transmit_rate": 0,
    "date": "2025-03-19T17:00:12.65792+01:00"
  },
  {
    "rssi": -61.25,
    "noise": -92.89,
    "transmit_rate": 0,
    "date": "2025-03-19T17:00:12.669154+01:00"
  },
  {
    "rssi": -61.16,
    "noise": -93.15,
    "transmit_rate": 0,
    "date": "2025-03-19T17:00:12.685079+01:00"
  },
  {
    "rssi": -61.28,
    "noise": -92.76,
    "transmit_rate": 0,
    "date": "2025-03-19T17:00:12.689785+01:00"
  },
  {
    "rssi": -60.73,
    "noise": -92.73,
    "transmit_rate": 0,
    "date": "2025-03-19T17:00:12.700445+01:00"
  },
  {
    "rssi": -61.13,
    "noise": -92.77,
    "transmit_rate": 0,
    "date": "2025-03-19T17:00:12.710851+01:00"
  },
  {
    "rssi": -60.86,
    "noise": -93.01,
    "transmit_rate": 0,
    "date": "2025-03-19T17:00:12.721434+01:00"
  },
  {
    "rssi": -61.14,
    "noise": -92.97,
    "transmit_rate": 287.08,
    "date": "2025-03-19T17:00:12.732454+01:00"
  },
  {
    "rssi": -61.79,
    "noise": -93.23,
    "transmit_rate": 282.72,
    "date": "2025-03-19T17:00:12.741854+01:00"
  },
  {
    "rssi": -62.17,
    "noise": -92.85,
    "transmit_rate": 285.05,
    "date": "2025-03-19T17:00:12.752746+01:00"
  },
  {
    "rssi": -61.81,
    "noise": -93.03,
    "transmit_rate": 290.03,
    "date": "2025-03-19T17:00:12.763146+01:00"
  },
  {
    "rssi": -61.81,
    "noise": -92.92,
    "transmit_rate": 290.89,
    "date": "2025-03-19T17:00:12.773923+01:00"
  },
  {
    "rssi": -62.01,
    "noise": -92.82,
    "transmit_rate": 285.37,
    "date": "2025-03-19T17:00:12.784968+01:00"
  },
  {
    "rssi": -62.15,
    "noise": -92.95,
    "transmit_rate": 289.71,
    "date": "2025-03-19T17:00:12.795031+01:00"
  },
  {
    "rssi": -61.9,
    "noise": -93.12,
    "transmit_rate": 286.53,
    "date": "2025-03-19T17:00:12.806241+01:00"
  },
  {
    "rssi": -62.23,
    "noise": -93.27,
    "transmit_rate": 287.31,
    "date": "2025-03-19T17:00:12.817261+01:00"
  },
  {
    "rssi": -62.23,
    "noise": -93.01,
    "transmit_rate": 286.95,
    "date": "2025-03-19T17:00:12.82685+01:00"
  },
  {
    "rssi": -62.24,
    "noise": -92.95,
    "transmit_rate": 286.56,
    "date": "2025-03-19T17:00:12.841402+01:00"
  },
  {
    "rssi": -61.91,
    "noise": -92.74,
    "transmit_rate": 286.08,
    "date": "2025-03-19T17:00:12.846123+01:00"
  },
  {
    "rssi": -61.3,
    "noise": -92.72,
    "transmit_rate": 290.02,
    "date": "2025-03-19T17:00:12.858825+01:00"
  },
  {
    "rssi": -61.11,
    "noise": -92.89,
    "transmit_rate": 289.3,
    "date": "2025-03-19T17:00:12.868461+01:00"
  },
  {
    "rssi": -60.95,
    "noise": -93.28,
    "transmit_rate": 281.61,
    "date": "2025-03-19T17:00:12.87974+01:00"
  },
  {
    "rssi": -60.98,
    "noise": -93,
    "transmit_rate": 281.95,
    "date": "2025-03-19T17:00:12.890311+01:00"
  },
  {
    "rssi": -60.7,
    "noise": -92.88,
    "transmit_rate": 282.91,
    "date": "2025-03-19T17:00:12.900955+01:00"
  },
  {
    "rssi": -61.25,
    "noise": -92.74,
    "transmit_rate": 284.86,
    "date": "2025-03-19T17:00:12.911167+01:00"
  },
  {
    "rssi": -60.83,
    "noise": -92.72,
    "transmit_rate": 281.69,
    "date": "2025-03-19T17:00:12.921906+01:00"
  },
  {
    "rssi": -60.81,
    "noise": -92.7,
    "transmit_rate": 282.3,
    "date": "2025-03-19T17:00:12.932574+01:00"
  },
  {
    "rssi": -61.2,
    "noise": -92.96,
    "transmit_rate": 283.6,
    "date": "2025-03-19T17:00:12.945774+01:00"
  },
  {
    "rssi": -60.85,
    "noise": -92.9,
    "transmit_rate": 284.59,
    "date": "2025-03-19T17:00:12.953516+01:00"
  },
  {
    "rssi": -61.16,
    "noise": -92.89,
    "transmit_rate": 288.71,
    "date": "2025-03-19T17:00:12.962718+01:00"
  },
  {
    "rssi": -61.24,
    "noise": -93.02,
    "transmit_rate": 287.45,
    "date": "2025-03-19T17:00:12.973386+01:00"
  },
  {
    "rssi": -60.97,
    "noise": -93.25,
    "transmit_rate": 281.31,
    "date": "2025-03-19T17:00:12.984493+01:00"
  },
  {
    "rssi": -60.99,
    "noise": -92.81,
    "transmit_rate": 281.34,
    "date": "2025-03-19T17:00:12.994615+01:00"
  },
  {
    "rssi": -61,
    "noise": -92.76,
    "transmit_rate": 282.63,
    "date": "2025-03-19T17:00:13.005327+01:00"
  },
  {
    "rssi": -60.7,
    "noise": -92.8,
    "transmit_rate": 288.47,
    "date": "2025-03-19T17:00:13.016734+01:00"
  },
  {
    "rssi": -61.09,
    "noise": -93.26,
    "transmit_rate": 282.54,
    "date": "2025-03-19T17:00:13.026397+01:00"
  },
  {
    "rssi": -61.14,
    "noise": -92.88,
    "transmit_rate": 290.69,
    "date": "2025-03-19T17:00:13.037255+01:00"
  },
  {
    "rssi": -60.85,
    "noise": -93.02,
    "transmit_rate": 283.11,
    "date": "2025-03-19T17:00:13.047914+01:00"
  },
  {
    "rssi": -60.84,
    "noise": -93.08,
    "transmit_rate": 286.66,
    "date": "2025-03-19T17:00:13.05811+01:00"
  },
  {
    "rssi": -61.29,
    "noise": -92.87,
    "transmit_rate": 287.47,
    "date": "2025-03-19T17:00:13.06837+01:00"
  },
  {
    "rssi": -61.23,
    "noise": -93.07,
    "transmit_rate": 290.08,
    "date": "2025-03-19T17:00:13.07902+01:00"
  },
  {
    "rssi": -61.23,
    "noise": -92.97,
    "transmit_rate": 289.04,
    "date": "2025-03-19T17:00:13.090043+01:00"
  },
  {
    "rssi": -61.21,
    "noise": -93,
    "transmit_rate": 287.78,
    "date": "2025-03-19T17:00:13.101036+01:00"
  },
  {
    "rssi": -60.98,
    "noise": -92.77,
    "transmit_rate": 281.35,
    "date": "2025-03-19T17:00:13.111026+01:00"
  },
  {
    "rssi": -61.2,
    "noise": -93.28,
    "transmit_rate": 289.51,
    "date": "2025-03-19T17:00:13.121741+01:00"
  }
]